pygen/__init__.py
pygen/cli.py
pygen/client.py
pygen/doctor.py
pygen/engine.py
pygen/health.py
pygen_py-0.1.0.dist-info/METADATA
pygen_py-0.1.0.dist-info/WHEEL
pygen_py-0.1.0.dist-info/entry_points.txt
pygen_py-0.1.0.dist-info/top_level.txt
pygen_py-0.1.0.dist-info/RECORD
