Metadata-Version: 2.4
Name: pygen-py
Version: 0.1.0
Summary: Python project generator with governance, plugins, and compliance
Author: PyGen Team
License: MIT
Keywords: cli,generator,devtools,compliance
Classifier: Programming Language :: Python :: 3
Classifier: License :: OSI Approved :: MIT License
Classifier: Operating System :: OS Independent
Requires-Python: >=3.10
Requires-Dist: pyyaml
